investment/__about__.py
investment/__init__.py
investment/__main__.py
investment/data/.DS_Store
investment/data/__init__.py
investment/data/_data.py
investment/data/_indicator.py
investment/data/_ticker.py
investment/data/__pycache__/__init__.cpython-38.pyc
investment/data/__pycache__/_data.cpython-38.pyc
investment/data/__pycache__/_index.cpython-38.pyc
investment/data/__pycache__/_indicator.cpython-38.pyc
investment/data/__pycache__/_ticker.cpython-38.pyc
investment/gui/__init__.py
investment/gui/_gui.py
investment/math_and_stats/__init__.py
investment/math_and_stats/_math.py
investment/math_and_stats/_stats.py
investment-0.2.17.dist-info/LICENSE
investment-0.2.17.dist-info/METADATA
investment-0.2.17.dist-info/WHEEL
investment-0.2.17.dist-info/top_level.txt
investment-0.2.17.dist-info/RECORD
