Metadata-Version: 2.1
Name: investment
Version: 0.2.17
Summary: A Python App for Investment
Home-page: https://github.com/investment-ml/investment
Author: Investment Prediction Enthusiast
Author-email: investment.ml.prediction@gmail.com
License: LGPL-3.0
Platform: UNKNOWN
Classifier: Programming Language :: Python :: 3
Classifier: Programming Language :: Python :: 3.6
Classifier: Programming Language :: Python :: 3.7
Classifier: Programming Language :: Python :: 3.8
Classifier: Programming Language :: Python :: 3.9
Classifier: License :: OSI Approved :: GNU Lesser General Public License v3 (LGPLv3)
Classifier: Operating System :: OS Independent
Requires-Python: >=3.6
Requires-Dist: matplotlib (>=3.3.2)
Requires-Dist: yfinance (>=0.1.59)
Requires-Dist: pandas (>=1.1.4)
Requires-Dist: PySide2 (>=5.15.2)
Requires-Dist: tables (>=3.6.1)
Requires-Dist: statsmodels (>=0.12.2)
Requires-Dist: csaps (>=1.0.3)
